pepboost/__init__.py
pepboost/__main__.py
pepboost/base.py
pepboost/cli.py
pepboost/training.py
pepboost/predictor/__init__.py
pepboost/predictor/align.py
pepboost/predictor/base.py
pepboost/predictor/charge_state.py
pepboost/predictor/constants.py
pepboost/predictor/encoder.py
pepboost/predictor/ion_mobility.py
pepboost/predictor/retention_time.py
pepboost-0.1.2.dist-info/LICENSE
pepboost-0.1.2.dist-info/METADATA
pepboost-0.1.2.dist-info/WHEEL
pepboost-0.1.2.dist-info/top_level.txt
pepboost-0.1.2.dist-info/RECORD
