Metadata-Version: 2.1
Name: pepboost
Version: 0.1.2
Summary: Awesome pepboost created by pgarrett-scripps
Home-page: https://github.com/pgarrett-scripps/pepboost/
Author: pgarrett-scripps
License-File: LICENSE
Requires-Dist: numpy~=2.0.1
Requires-Dist: uniplot~=0.13.0
Requires-Dist: xgboost~=2.1.1
Requires-Dist: scikit-learn~=1.5.1
Requires-Dist: pandas~=2.2.2
Provides-Extra: test
Requires-Dist: pytest; extra == "test"
Requires-Dist: coverage; extra == "test"
Requires-Dist: flake8; extra == "test"
Requires-Dist: black; extra == "test"
Requires-Dist: isort; extra == "test"
Requires-Dist: pytest-cov; extra == "test"
Requires-Dist: mypy; extra == "test"
Requires-Dist: gitchangelog; extra == "test"
Requires-Dist: mkdocs; extra == "test"
